README.md
setup.py
ph7/__init__.py
ph7/context.py
ph7/css.py
ph7/formatters.py
ph7/html.py
ph7/py.typed
ph7/static.py
ph7/style.py
ph7.egg-info/PKG-INFO
ph7.egg-info/SOURCES.txt
ph7.egg-info/dependency_links.txt
ph7.egg-info/top_level.txt
ph7/core/__init__.py
ph7/core/css.py
ph7/core/html.py
ph7/core/tags.py
ph7/django/__init__.py
ph7/django/engine.py
ph7/flask/__init__.py
ph7/flask/engine.py
ph7/js/__init__.py
ph7/js/events.py
ph7/js/transpile.py
ph7/js/lib/__init__.py
ph7/js/lib/_mock.py
ph7/js/lib/api.py
tests/test_examples.py