Metadata-Version: 2.1
Name: ph7
Version: 0.1.0rc5
Summary: Python native web templates
Home-page: https://github.com/angrybayblade/ph7
Author: Viraj Patel
Author-email: vptl185@gmail.com
Project-URL: Documentation, http://ph7.angrybayblade.me
Project-URL: Changelog, https://github.com/angrybayblade/ph7/blob/main/docs/CHANGELOG.md
Project-URL: Issue Tracker, https://github.com/angrybayblade/ph7/issues
Keywords: html,css,js,templates,django
Classifier: Development Status :: 3 - Alpha
Classifier: Intended Audience :: Developers
Classifier: Framework :: Django
Classifier: License :: OSI Approved :: MIT License
Classifier: Programming Language :: Python :: 3.7
Classifier: Programming Language :: Python :: 3.8
Classifier: Programming Language :: Python :: 3.9
Classifier: Programming Language :: Python :: 3.10
Classifier: Programming Language :: Python :: 3.11
Requires-Python: >=3.9, <4
